{
  "generated_at": "2026-05-30T04:55:21.403Z",
  "next_update": "2026-05-30T10:55:21.403Z",
  "data": {
    "brent": {
      "symbol": "cb.f",
      "name": "Brent Crude",
      "value": 91.12,
      "change_pct": -0.5131564581286153,
      "change_abs": -0.46999999999999886,
      "previous_close": 91.59,
      "timestamp": "2026-05-29T23:00:00Z"
    },
    "sp500": {
      "symbol": "^spx",
      "name": "S&P 500",
      "value": 7580.1,
      "change_pct": 0,
      "change_abs": 0,
      "previous_close": 7580.1,
      "timestamp": "2026-05-29T23:00:00Z"
    },
    "dxy": {
      "symbol": "dx.f",
      "name": "DXY",
      "value": 98.852,
      "change_pct": -0.04853387259858627,
      "change_abs": -0.04800000000000182,
      "previous_close": 98.9,
      "timestamp": "2026-05-29T23:00:00Z"
    },
    "usdbrl": {
      "symbol": "usdbrl",
      "name": "USD/BRL",
      "value": 5.0515,
      "change_pct": 0,
      "change_abs": 0,
      "previous_close": 5.0515,
      "timestamp": "2026-05-29T18:59:56Z"
    },
    "ibov": {
      "symbol": "^bvp",
      "name": "IBOV",
      "value": 173787.49,
      "change_pct": 0.000005754154430577735,
      "change_abs": 0.009999999980209395,
      "previous_close": 173787.48,
      "timestamp": "2026-05-29T23:00:00Z"
    },
    "vix": {
      "symbol": "VIXY",
      "name": "VIX (proxy: VIXY ETF)",
      "value": 23.29,
      "change_pct": -1.72996,
      "change_abs": -0.40999985,
      "previous_close": 23.7,
      "timestamp": "2026-05-29Z"
    },
    "btc": {
      "symbol": "BTC-USD",
      "name": "Bitcoin",
      "value": 73281,
      "change_pct": -0.16338604537096887,
      "change_abs": -119.7309279082997,
      "previous_close": 73400.7309279083,
      "timestamp": "2026-05-30T04:55:21.403Z"
    }
  },
  "errors": []
}