{
  "generated_at": "2026-05-31T20:18:03.754Z",
  "next_update": "2026-06-01T02:18:03.754Z",
  "prices": {
    "BTC": {
      "symbol": "BTC",
      "source": "coingecko",
      "value": 73559,
      "change_pct": -0.4062083233081915,
      "change_abs": -298.8027805422726,
      "previous_close": 73857.80278054228,
      "timestamp": "2026-05-31T20:18:03.298Z"
    }
  },
  "errors": [
    "twelvedata-batch: HTTP 429",
    "BBAS3: no data",
    "BRAP4: no data",
    "CPFE3: no data",
    "KLBN3: no data",
    "JBSS3: no data",
    "SANB11: no data",
    "SAPR4: no data"
  ]
}