{
  "generated_at": "2026-07-10T15:30:30.085Z",
  "next_update": "2026-07-10T21:30:30.085Z",
  "prices": {
    "BTC": {
      "symbol": "BTC",
      "source": "coingecko",
      "value": 64098,
      "change_pct": 1.729564853101666,
      "change_abs": 1108.616479541106,
      "previous_close": 62989.3835204589,
      "timestamp": "2026-07-10T15:30:29.569Z"
    }
  },
  "errors": [
    "twelvedata-batch: HTTP 429",
    "BBAS3: HTTP 404",
    "BRAP4: HTTP 404",
    "CPFE3: HTTP 404",
    "JBSS3: HTTP 404",
    "KLBN3: HTTP 404",
    "SANB11: HTTP 404",
    "SAPR4: HTTP 404"
  ]
}